ClockDivider.v
module ClockDivider( 
    input clk_in,
    output reg clk_out
);
    reg [25:0] counter = 0;

    always @(posedge clk_in) begin
        if (counter == 10000000 - 1) begin
            counter <= 0;
            clk_out <= ~clk_out;  // Toggle clk_out
        end else begin
            counter <= counter + 1;
        end
    end
endmodule

testbench/ClockDivider_tb.v
`timescale 1ns / 1ps

module ClockDivider_tb;
    reg clk_in;
    wire clk_out;

    ClockDivider uut (
        .clk_in(clk_in),
        .clk_out(clk_out)
    );

    initial begin
        clk_in = 0;
    end
        
    always #12.5 clk_in = ~clk_in; // 40 MHz clock -> 25 ns period -> 12.5 ns half period

    initial begin
        $dumpfile("build/clockdivider.vcd");
        $dumpvars(0, ClockDivider_tb);
        $monitor("Time = %0t | clk_in = %b | clk_out = %b", $time, clk_in, clk_out);

        // 1000 million ns, or 1s
        #1000000000;
        
        $finish;
    end
endmodule

build/clockdivider.vcd
$date
	Mon Dec 09 17:39:36 2024
$end
$version
	Icarus Verilog
$end
$timescale
	1ps
$end
$scope module ClockDivider_tb $end
$var wire 1 ! clk_out $end
$var reg 1 " clk_in $end
$scope module uut $end
$var wire 1 " clk_in $end
$var reg 1 ! clk_out $end
$var reg 26 # counter [25:0] $end
$upscope $end
$upscope $end
$enddefinitions $end
#0
$dumpvars
b0 #
0"
0!
$end
#12500
b1 #
1"
#25000
0"
#37500
b10 #
1"
#50000
0"
#62500
b11 #
1"
#75000
0"
#87500
b100 #
1"
#100000
0"
#112500
b101 #
1"
#125000
0"
#137500
b110 #
1"
#150000
0"
#162500
b111 #
1"
#175000
0"
#187500
b1000 #
1"
#200000
0"
#212500
b1001 #
1"
#225000
0"
#237500
b1010 #
1"
#250000
0"
#262500
b1011 #
1"
#275000
0"
#287500
b1100 #
1"
#300000
0"
#312500
b1101 #
1"
#325000
0"
#337500
b1110 #
1"
#350000
0"
#362500
b1111 #
1"
#375000
0"
#387500
b10000 #
1"
#400000
0"
#412500
b10001 #
1"
#425000
0"
#437500
b10010 #
1"
#450000
0"
#462500
b10011 #
1"
#475000
0"
#487500
b10100 #
1"
#500000
0"
#512500
b10101 #
1"
#525000
0"
#537500
b10110 #
1"
#550000
0"
#562500
b10111 #
1"
#575000
0"
#587500
b11000 #
1"
#600000
0"
#612500
b11001 #
1"
#625000
0"
#637500
b11010 #
1"
#650000
0"
#662500
b11011 #
1"
#675000
0"
#687500
b11100 #
1"
#700000
0"
#712500
b11101 #
1"
#725000
0"
#737500
b11110 #
1"
#750000
0"
#762500
b11111 #
1"
#775000
0"
#787500
b100000 #
1"
#800000
0"
#812500
b100001 #
1"
#825000
0"
#837500
b100010 #
1"
#850000
0"
#862500
b100011 #
1"
#875000
0"
#887500
b100100 #
1"
#900000
0"
#912500
b100101 #
1"
#925000
0"
#937500
b100110 #
1"
#950000
0"
#962500
b100111 #
1"
#975000
0"
#987500
b101000 #
1"
#1000000
0"
#1012500
b101001 #
1"
#1025000
0"
#1037500
b101010 #
1"
#1050000
0"
#1062500
b101011 #
1"
#1075000
0"
#1087500
b101100 #
1"
#1100000
0"
#1112500
b101101 #
1"
#1125000
0"
#1137500
b101110 #
1"
#1150000
0"
#1162500
b101111 #
1"
#1175000
0"
#1187500
b110000 #
1"
#1200000
0"
#1212500
b110001 #
1"
#1225000
0"
#1237500
b110010 #
1"
#1250000
0"
#1262500
b110011 #
1"
#1275000
0"
#1287500
b110100 #
1"
#1300000
0"
#1312500
b110101 #
1"
#1325000
0"
#1337500
b110110 #
1"
#1350000
0"
#1362500
b110111 #
1"
#1375000
0"
#1387500
b111000 #
1"
#1400000
0"
#1412500
b111001 #
1"
#1425000
0"
#1437500
b111010 #
1"
#1450000
0"
#1462500
b111011 #
1"
#1475000
0"
#1487500
b111100 #
1"
#1500000
0"
#1512500
b111101 #
1"
#1525000
0"
#1537500
b111110 #
1"
#1550000
0"
#1562500
b111111 #
1"
#1575000
0"
#1587500
b1000000 #
1"
#1600000
0"
#1612500
b1000001 #
1"
#1625000
0"
#1637500
b1000010 #
1"
#1650000
0"
#1662500
b1000011 #
1"
#1675000
0"
#1687500
b1000100 #
1"
#1700000
0"
#1712500
b1000101 #
1"
#1725000
0"
#1737500
b1000110 #
1"
#1750000
0"
#1762500
b1000111 #
1"
#1775000
0"
#1787500
b1001000 #
1"
#1800000
0"
#1812500
b1001001 #
1"
#1825000
0"
#1837500
b1001010 #
1"
#1850000
0"
#1862500
b1001011 #
1"
#1875000
0"
#1887500
b1001100 #
1"
#1900000
0"
#1912500
b1001101 #
1"
#1925000
0"
#1937500
b1001110 #
1"
#1950000
0"
#1962500
b1001111 #
1"
#1975000
0"
#1987500
b1010000 #
1"
#2000000
0"
#2012500
b1010001 #
1"
#2025000
0"
#2037500
b1010010 #
1"
#2050000
0"
#2062500
b1010011 #
1"
#2075000
0"
#2087500
b1010100 #
1"
#2100000
0"
#2112500
b1010101 #
1"
#2125000
0"
#2137500
b1010110 #
1"
#2150000
0"
#2162500
b1010111 #
1"
#2175000
0"
#2187500
b1011000 #
1"
#2200000
0"
#2212500
b1011001 #
1"
#2225000
0"
#2237500
b1011010 #
1"
#2250000
0"
#2262500
b1011011 #
1"
#2275000
0"
#2287500
b1011100 #
1"
#2300000
0"
#2312500
b1011101 #
1"
#2325000
0"
#2337500
b1011110 #
1"
#2350000
0"
#2362500
b1011111 #
1"
#2375000
0"
#2387500
b1100000 #
1"
#2400000
0"
#2412500
b1100001 #
1"
#2425000
0"
#2437500
b1100010 #
1"
#2450000
0"
#2462500
b1100011 #
1"
#2475000
0"
#2487500
b1100100 #
1"
#2500000
0"
#2512500
b1100101 #
1"
#2525000
0"
#2537500
b1100110 #
1"
#2550000
0"
#2562500
b1100111 #
1"
#2575000
0"
#2587500
b1101000 #
1"
#2600000
0"
#2612500
b1101001 #
1"
#2625000
0"
#2637500
b1101010 #
1"
#2650000
0"
#2662500
b1101011 #
1"
#2675000
0"
#2687500
b1101100 #
1"
#2700000
0"
#2712500
b1101101 #
1"
#2725000
0"
#2737500
b1101110 #
1"
#2750000
0"
#2762500
b1101111 #
1"
#2775000
0"
#2787500
b1110000 #
1"
#2800000
0"
#2812500
b1110001 #
1"
#2825000
0"
#2837500
b1110010 #
1"
#2850000
0"
#2862500
b1110011 #
1"
#2875000
0"
#2887500
b1110100 #
1"
#2900000
0"
#2912500
b1110101 #
1"
#2925000
0"
#2937500
b1110110 #
1"
#2950000
0"
#2962500
b1110111 #
1"
#2975000
0"
#2987500
b1111000 #
1"
#3000000
0"
#3012500
b1111001 #
1"
#3025000
0"
#3037500
b1111010 #
1"
#3050000
0"
#3062500
b1111011 #
1"
#3075000
0"
#3087500
b1111100 #
1"
#3100000
0"
#3112500
b1111101 #
1"
#3125000
0"
#3137500
b1111110 #
1"
#3150000
0"
#3162500
b1111111 #
1"
#3175000
0"
#3187500
b10000000 #
1"
#3200000
0"
#3212500
b10000001 #
1"
#3225000
0"
#3237500
b10000010 #
1"
#3250000
0"
#3262500
b10000011 #
1"
#3275000
0"
#3287500
b10000100 #
1"
#3300000
0"
#3312500
b10000101 #
1"
#3325000
0"
#3337500
b10000110 #
1"
#3350000
0"
#3362500
b10000111 #
1"
#3375000
0"
#3387500
b10001000 #
1"
#3400000
0"
#3412500
b10001001 #
1"
#3425000
0"
#3437500
b10001010 #
1"
#3450000
0"
#3462500
b10001011 #
1"
#3475000
0"
#3487500
b10001100 #
1"
#3500000
0"
#3512500
b10001101 #
1"
#3525000
0"
#3537500
b10001110 #
1"
#3550000
0"
#3562500
b10001111 #
1"
#3575000
0"
#3587500
b10010000 #
1"
#3600000
0"
#3612500
b10010001 #
1"
#3625000
0"
#3637500
b10010010 #
1"
#3650000
0"
#3662500
b10010011 #
1"
#3675000
0"
#3687500
b10010100 #
1"
#3700000
0"
#3712500
b10010101 #
1"
#3725000
0"
#3737500
b10010110 #
1"
#3750000
0"
#3762500
b10010111 #
1"
#3775000
0"
#3787500
b10011000 #
1"
#3800000
0"
#3812500
b10011001 #
1"
#3825000
0"
#3837500
b10011010 #
1"
#3850000
0"
#3862500
b10011011 #
1"
#3875000
0"
#3887500
b10011100 #
1"
#3900000
0"
#3912500
b10011101 #
1"
#3925000
0"
#3937500
b10011110 #
1"
#3950000
0"
#3962500
b10011111 #
1"
#3975000
0"
#3987500
b10100000 #
1"
#4000000
0"
#4012500
b10100001 #
1"
#4025000
0"
#4037500
b10100010 #
1"
#4050000
0"
#4062500
b10100011 #
1"
#4075000
0"
#4087500
b10100100 #
1"
#4100000
0"
#4112500
b10100101 #
1"
#4125000
0"
#4137500
b10100110 #
1"
#4150000
0"
#4162500
b10100111 #
1"
#4175000
0"
#4187500
b10101000 #
1"
#4200000
0"
#4212500
b10101001 #
1"
#4225000
0"
#4237500
b10101010 #
1"
#4250000
0"
#4262500
b10101011 #
1"
#4275000
0"
#4287500
b10101100 #
1"
#4300000
0"
#4312500
b10101101 #
1"
#4325000
0"
#4337500
b10101110 #
1"
#4350000
0"
#4362500
b10101111 #
1"
#4375000
0"
#4387500
b10110000 #
1"
#4400000
0"
#4412500
b10110001 #
1"
#4425000
0"
#4437500
b10110010 #
1"
#4450000
0"
#4462500
b10110011 #
1"
#4475000
0"
#4487500
b10110100 #
1"
#4500000
0"
#4512500
b10110101 #
1"
#4525000
0"
#4537500
b10110110 #
1"
#4550000
0"
#4562500
b10110111 #
1"
#4575000
0"
#4587500
b10111000 #
1"
#4600000
0"
#4612500
b10111001 #
1"
#4625000
0"
#4637500
b10111010 #
1"
#4650000
0"
#4662500
b10111011 #
1"
#4675000
0"
#4687500
b10111100 #
1"
#4700000
0"
#4712500
b10111101 #
1"
#4725000
0"
#4737500
b10111110 #
1"
#4750000
0"
#4762500
b10111111 #
1"
#4775000
0"
#4787500
b11000000 #
1"
#4800000
0"
#4812500
b11000001 #
1"
#4825000
0"
#4837500
b11000010 #
1"
#4850000
0"
#4862500
b11000011 #
1"
#4875000
0"
#4887500
b11000100 #
1"
#4900000
0"
#4912500
b11000101 #
1"
#4925000
0"
#4937500
b11000110 #
1"
#4950000
0"
#4962500
b11000111 #
1"
#4975000
0"
#4987500
b11001000 #
1"
#5000000
0"
#5012500
b11001001 #
1"
#5025000
0"
#5037500
b11001010 #
1"
#5050000
0"
#5062500
b11001011 #
1"
#5075000
0"
#5087500
b11001100 #
1"
#5100000
0"
#5112500
b11001101 #
1"
#5125000
0"
#5137500
b11001110 #
1"
#5150000
0"
#5162500
b11001111 #
1"
#5175000
0"
#5187500
b11010000 #
1"
#5200000
0"
#5212500
b11010001 #
1"
#5225000
0"
#5237500
b11010010 #
1"
#5250000
0"
#5262500
b11010011 #
1"
#5275000
0"
#5287500
b11010100 #
1"
#5300000
0"
#5312500
b11010101 #
1"
#5325000
0"
#5337500
b11010110 #
1"
#5350000
0"
#5362500
b11010111 #
1"
#5375000
0"
#5387500
b11011000 #
1"
#5400000
0"
#5412500
b11011001 #
1"
#5425000
0"
#5437500
b11011010 #
1"
#5450000
0"
#5462500
b11011011 #
1"
#5475000
0"
#5487500
b11011100 #
1"
#5500000
0"
#5512500
b11011101 #
1"
#5525000
0"
#5537500
b11011110 #
1"
#5550000
0"
#5562500
b11011111 #
1"
#5575000
0"
#5587500
b11100000 #
1"
#5600000
0"
#5612500
b11100001 #
1"
#5625000
0"
#5637500
b11100010 #
1"
#5650000
0"
#5662500
b11100011 #
1"
#5675000
0"
#5687500
b11100100 #
1"
#5700000
0"
#5712500
b11100101 #
1"
#5725000
0"
#5737500
b11100110 #
1"
#5750000
0"
#5762500
b11100111 #
1"
#5775000
0"
#5787500
b11101000 #
1"
#5800000
0"
#5812500
b11101001 #
1"
#5825000
0"
#5837500
b11101010 #
1"
#5850000
0"
#5862500
b11101011 #
1"
#5875000
0"
#5887500
b11101100 #
1"
#5900000
0"
#5912500
b11101101 #
1"
#5925000
0"
#5937500
b11101110 #
1"
#5950000
0"
#5962500
b11101111 #
1"
#5975000
0"
#5987500
b11110000 #
1"
#6000000
0"
#6012500
b11110001 #
1"
#6025000
0"
#6037500
b11110010 #
1"
#6050000
0"
#6062500
b11110011 #
1"
#6075000
0"
#6087500
b11110100 #
1"
#6100000
0"
#6112500
b11110101 #
1"
#6125000
0"
#6137500
b11110110 #
1"
#6150000
0"
#6162500
b11110111 #
1"
#6175000
0"
#6187500
b11111000 #
1"
#6200000
0"
#6212500
b11111001 #
1"
#6225000
0"
#6237500
b11111010 #
1"
#6250000
0"
#6262500
b11111011 #
1"
#6275000
0"
#6287500
b11111100 #
1"
#6300000
0"
#6312500
b11111101 #
1"
#6325000
0"
#6337500
b11111110 #
1"
#6350000
0"
#6362500
b11111111 #
1"
#6375000
0"
#6387500
b100000000 #
1"
#6400000
0"
#6412500
b100000001 #
1"
#6425000
0"
#6437500
b100000010 #
1"
#6450000
0"
#6462500
b100000011 #
1"
#6475000
0"
#6487500
b100000100 #
1"
#6500000
0"
#6512500
b100000101 #
1"
#6525000
0"
#6537500
b100000110 #
1"
#6550000
0"
#6562500
b100000111 #
1"
#6575000
0"
#6587500
b100001000 #
1"
#6600000
0"
#6612500
b100001001 #
1"
#6625000
0"
#6637500
b100001010 #
1"
#6650000
0"
#6662500
b100001011 #
1"
#6675000
0"
#6687500
b100001100 #
1"
#6700000
0"
#6712500
b100001101 #
1"
#6725000
0"
#6737500
b100001110 #
1"
#6750000
0"
#6762500
b100001111 #
1"
#6775000
0"
#6787500
b100010000 #
1"
#6800000
0"
#6812500
b100010001 #
1"
#6825000
0"
#6837500
b100010010 #
1"
#6850000
0"
#6862500
b100010011 #
1"
#6875000
0"
#6887500
b100010100 #
1"
#6900000
0"
#6912500
b100010101 #
1"
#6925000
0"
#6937500
b100010110 #
1"
#6950000
0"
#6962500
b100010111 #
1"
#6975000
0"
#6987500
b100011000 #
1"
#7000000
0"
#7012500
b100011001 #
1"
#7025000
0"
#7037500
b100011010 #
1"
#7050000
0"
#7062500
b100011011 #
1"
#7075000
0"
#7087500
b100011100 #
1"
#7100000
0"
#7112500
b100011101 #
1"
#7125000
0"
#7137500
b100011110 #
1"
#7150000
0"
#7162500
b100011111 #
1"
#7175000
0"
#7187500
b100100000 #
1"
#7200000
0"
#7212500
b100100001 #
1"
#7225000
0"
#7237500
b100100010 #
1"
#7250000
0"
#7262500
b100100011 #
1"
#7275000
0"
#7287500
b100100100 #
1"
#7300000
0"
#7312500
b100100101 #
1"
#7325000
0"
#7337500
b100100110 #
1"
#7350000
0"
#7362500
b100100111 #
1"
#7375000
0"
#7387500
b100101000 #
1"
#7400000
0"
#7412500
b100101001 #
1"
#7425000
0"
#7437500
b100101010 #
1"
#7450000
0"
#7462500
b100101011 #
1"
#7475000
0"
#7487500
b100101100 #
1"
#7500000
0"
#7512500
b100101101 #
1"
#7525000
0"
#7537500
b100101110 #
1"
#7550000
0"
#7562500
b100101111 #
1"
#7575000
0"
#7587500
b100110000 #
1"
#7600000
0"
#7612500
b100110001 #
1"
#7625000
0"
#7637500
b100110010 #
1"
#7650000
0"
#7662500
b100110011 #
1"
#7675000
0"
#7687500
b100110100 #
1"
#7700000
0"
#7712500
b100110101 #
1"
#7725000
0"
#7737500
b100110110 #
1"
#7750000
0"
#7762500
b100110111 #
1"
#7775000
0"
#7787500
b100111000 #
1"
#7800000
0"
#7812500
b100111001 #
1"
#7825000
0"
#7837500
b100111010 #
1"
#7850000
0"
#7862500
b100111011 #
1"
#7875000
0"
#7887500
b100111100 #
1"
#7900000
0"
#7912500
b100111101 #
1"
#7925000
0"
#7937500
b100111110 #
1"
#7950000
0"
#7962500
b100111111 #
1"
#7975000
0"
#7987500
b101000000 #
1"
#8000000
0"
#8012500
b101000001 #
1"
#8025000
0"
#8037500
b101000010 #
1"
#8050000
0"
#8062500
b101000011 #
1"
#8075000
0"
#8087500
b101000100 #
1"
#8100000
0"
#8112500
b101000101 #
1"
#8125000
0"
#8137500
b101000110 #
1"
#8150000
0"
#8162500
b101000111 #
1"
#8175000
0"
#8187500
b101001000 #
1"
#8200000
0"
#8212500
b101001001 #
1"
#8225000
0"
#8237500
b101001010 #
1"
#8250000
0"
#8262500
b101001011 #
1"
#8275000
0"
#8287500
b101001100 #
1"
#8300000
0"
#8312500
b101001101 #
1"
#8325000
0"
#8337500
b101001110 #
1"
#8350000
0"
#8362500
b101001111 #
1"
#8375000
0"
#8387500
b101010000 #
1"
#8400000
0"
#8412500
b101010001 #
1"
#8425000
0"
#8437500
b101010010 #
1"
#8450000
0"
#8462500
b101010011 #
1"
#8475000
0"
#8487500
b101010100 #
1"
#8500000
0"
#8512500
b101010101 #
1"
#8525000
0"
#8537500
b101010110 #
1"
#8550000
0"
#8562500
b101010111 #
1"
#8575000
0"
#8587500
b101011000 #
1"
#8600000
0"
#8612500
b101011001 #
1"
#8625000
0"
#8637500
b101011010 #
1"
#8650000
0"
#8662500
b101011011 #
1"
#8675000
0"
#8687500
b101011100 #
1"
#8700000
0"
#8712500
b101011101 #
1"
#8725000
0"
#8737500
b101011110 #
1"
#8750000
0"
#8762500
b101011111 #
1"
#8775000
0"
#8787500
b101100000 #
1"
#8800000
0"
#8812500
b101100001 #
1"
#8825000
0"
#8837500
b101100010 #
1"
#8850000
0"
#8862500
b101100011 #
1"
#8875000
0"
#8887500
b101100100 #
1"
#8900000
0"
#8912500
b101100101 #
1"
#8925000
0"
#8937500
b101100110 #
1"
#8950000
0"
#8962500
b101100111 #
1"
#8975000
0"
#8987500
b101101000 #
1"
#9000000
0"
#9012500
b101101001 #
1"
#9025000
0"
#9037500
b101101010 #
1"
#9050000
0"
#9062500
b101101011 #
1"
#9075000
0"
#9087500
b101101100 #
1"
#9100000
0"
#9112500
b101101101 #
1"
#9125000
0"
#9137500
b101101110 #
1"
#9150000
0"
#9162500
b101101111 #
1"
#9175000
0"
#9187500
b101110000 #
1"
#9200000
0"
#9212500
b101110001 #
1"
#9225000
0"
#9237500
b101110010 #
1"
#9250000
0"
#9262500
b101110011 #
1"
#9275000
0"
#9287500
b101110100 #
1"
#9300000
0"
#9312500
b101110101 #
1"
#9325000
0"
#9337500
b101110110 #
1"
#9350000
0"
#9362500
b101110111 #
1"
#9375000
0"
#9387500
b101111000 #
1"
#9400000
0"
#9412500
b101111001 #
1"
#9425000
0"
#9437500
b101111010 #
1"
#9450000
0"
#9462500
b101111011 #
1"
#9475000
0"
#9487500
b101111100 #
1"
#9500000
0"
#9512500
b101111101 #
1"
#9525000
0"
#9537500
b101111110 #
1"
#9550000
0"
#9562500
b101111111 #
1"
#9575000
0"
#9587500
b110000000 #
1"
#9600000
0"
#9612500
b110000001 #
1"
#9625000
0"
#9637500
b110000010 #
1"
#9650000
0"
#9662500
b110000011 #
1"
#9675000
0"
#9687500
b110000100 #
1"
#9700000
0"
#9712500
b110000101 #
1"
#9725000
0"
#9737500
b110000110 #
1"
#9750000
0"
#9762500
b110000111 #
1"
#9775000
0"
#9787500
b110001000 #
1"
#9800000
0"
#9812500
b110001001 #
1"
#9825000
0"
#9837500
b110001010 #
1"
#9850000
0"
#9862500
b110001011 #
1"
#9875000
0"
#9887500
b110001100 #
1"
#9900000
0"
#9912500
b110001101 #
1"
#9925000
0"
#9937500
b110001110 #
1"
#9950000
0"
#9962500
b110001111 #
1"
#9975000
0"
#9987500
b110010000 #
1"
#10000000
0"
#10012500
b110010001 #
1"
#10025000
0"
#10037500
b110010010 #
1"
#10050000
0"
#10062500
b110010011 #
1"
#10075000
0"
#10087500
b110010100 #
1"
#10100000
0"
#10112500
b110010101 #
1"
#10125000
0"
#10137500
b110010110 #
1"
#10150000
0"
#10162500
b110010111 #
1"
#10175000
0"
#10187500
b110011000 #
1"
#10200000
0"
#10212500
b110011001 #
1"
#10225000
0"
#10237500
b110011010 #
1"
#10250000
0"
#10262500
b110011011 #
1"
#10275000
0"
#10287500
b110011100 #
1"
#10300000
0"
#10312500
b110011101 #
1"
#10325000
0"
#10337500
b110011110 #
1"
#10350000
0"
#10362500
b110011111 #
1"
#10375000
0"
#10387500
b110100000 #
1"
#10400000
0"
#10412500
b110100001 #
1"
#10425000
0"
#10437500
b110100010 #
1"
#10450000
0"
#10462500
b110100011 #
1"
#10475000
0"
#10487500
b110100100 #
1"
#10500000
0"
#10512500
b110100101 #
1"
#10525000
0"
#10537500
b110100110 #
1"
#10550000
0"
#10562500
b110100111 #
1"
#10575000
0"
#10587500
b110101000 #
1"
#10600000
0"
#10612500
b110101001 #
1"
#10625000
0"
#10637500
b110101010 #
1"
#10650000
0"
#10662500
b110101011 #
1"
#10675000
0"
#10687500
b110101100 #
1"
#10700000
0"
#10712500
b110101101 #
1"
#10725000
0"
#10737500
b110101110 #
1"
#10750000
0"
#10762500
b110101111 #
1"
#10775000
0"
#10787500
b110110000 #
1"
#10800000
0"
#10812500
b110110001 #
1"
#10825000
0"
#10837500
b110110010 #
1"
#10850000
0"
#10862500
b110110011 #
1"
#10875000
0"
#10887500
b110110100 #
1"
#10900000
0"
#10912500
b110110101 #
1"
#10925000
0"
#10937500
b110110110 #
1"
#10950000
0"
#10962500
b110110111 #
1"
#10975000
0"
#10987500
b110111000 #
1"
#11000000
0"
#11012500
b110111001 #
1"
#11025000
0"
#11037500
b110111010 #
1"
#11050000
0"
#11062500
b110111011 #
1"
#11075000
0"
#11087500
b110111100 #
1"
#11100000
0"
#11112500
b110111101 #
1"
#11125000
0"
#11137500
b110111110 #
1"
#11150000
0"
#11162500
b110111111 #
1"
#11175000
0"
#11187500
b111000000 #
1"
#11200000
0"
#11212500
b111000001 #
1"
#11225000
0"
#11237500
b111000010 #
1"
#11250000
0"
#11262500
b111000011 #
1"
#11275000
0"
#11287500
b111000100 #
1"
#11300000
0"
#11312500
b111000101 #
1"
#11325000
0"
#11337500
b111000110 #
1"
#11350000
0"
#11362500
b111000111 #
1"
#11375000
0"
#11387500
b111001000 #
1"
#11400000
0"
#11412500
b111001001 #
1"
#11425000
0"
#11437500
b111001010 #
1"
#11450000
0"
#11462500
b111001011 #
1"
#11475000
0"
#11487500
b111001100 #
1"
#11500000
0"
#11512500
b111001101 #
1"
#11525000
0"
#11537500
b111001110 #
1"
#11550000
0"
#11562500
b111001111 #
1"
#11575000
0"
#11587500
b111010000 #
1"
#11600000
0"
#11612500
b111010001 #
1"
#11625000
0"
#11637500
b111010010 #
1"
#11650000
0"
#11662500
b111010011 #
1"
#11675000
0"
#11687500
b111010100 #
1"
#11700000
0"
#11712500
b111010101 #
1"
#11725000
0"
#11737500
b111010110 #
1"
#11750000
0"
#11762500
b111010111 #
1"
#11775000
0"
#11787500
b111011000 #
1"
#11800000
0"
#11812500
b111011001 #
1"
#11825000
0"
#11837500
b111011010 #
1"
#11850000
0"
#11862500
b111011011 #
1"
#11875000
0"
#11887500
b111011100 #
1"
#11900000
0"
#11912500
b111011101 #
1"
#11925000
0"
#11937500
b111011110 #
1"
#11950000
0"
#11962500
b111011111 #
1"
#11975000
0"
#11987500
b111100000 #
1"
#12000000
0"
#12012500
b111100001 #
1"
#12025000
0"
#12037500
b111100010 #
1"
#12050000
0"
#12062500
b111100011 #
1"
#12075000
0"
#12087500
b111100100 #
1"
#12100000
0"
#12112500
b111100101 #
1"
#12125000
0"
#12137500
b111100110 #
1"
#12150000
0"
#12162500
b111100111 #
1"
#12175000
0"
#12187500
b111101000 #
1"
#12200000
0"
#12212500
b111101001 #
1"
#12225000
0"
#12237500
b111101010 #
1"
#12250000
0"
#12262500
b111101011 #
1"
#12275000
0"
#12287500
b111101100 #
1"
#12300000
0"
#12312500
b111101101 #
1"
#12325000
0"
#12337500
b111101110 #
1"
#12350000
0"
#12362500
b111101111 #
1"
#12375000
0"
#12387500
b111110000 #
1"
#12400000
0"
#12412500
b111110001 #
1"
#12425000
0"
#12437500
b111110010 #
1"
#12450000
0"
#12462500
b111110011 #
1"
#12475000
0"
#12487500
b111110100 #
1"
#12500000
0"
#12512500
b111110101 #
1"
#12525000
0"
#12537500
b111110110 #
1"
#12550000
0"
#12562500
b111110111 #
1"
#12575000
0"
#12587500
b111111000 #
1"
#12600000
0"
#12612500
b111111001 #
1"
#12625000
0"
#12637500
b111111010 #
1"
#12650000
0"
#12662500
b111111011 #
1"
#12675000
0"
#12687500
b111111100 #
1"
#12700000
0"
#12712500
b111111101 #
1"
#12725000
0"
#12737500
b111111110 #
1"
#12750000
0"
#12762500
b111111111 #
1"
#12775000
0"
#12787500
b1000000000 #
1"
#12800000
0"
#12812500
b1000000001 #
1"
#12825000
0"
#12837500
b1000000010 #
1"
#12850000
0"
#12862500
b1000000011 #
1"
#12875000
0"
#12887500
b1000000100 #
1"
#12900000
0"
#12912500
b1000000101 #
1"
#12925000
0"
#12937500
b1000000110 #
1"
#12950000
0"
#12962500
b1000000111 #
1"
#12975000
0"
#12987500
b1000001000 #
1"
#13000000
0"
#13012500
b1000001001 #
1"
#13025000
0"
#13037500
b1000001010 #
1"
#13050000
0"
#13062500
b1000001011 #
1"
#13075000
0"
#13087500
b1000001100 #
1"
#13100000
0"
#13112500
b1000001101 #
1"
#13125000
0"
#13137500
b1000001110 #
1"
#13150000
0"
#13162500
b1000001111 #
1"
#13175000
0"
#13187500
b1000010000 #
1"
#13200000
0"
#13212500
b1000010001 #
1"
#13225000
0"
#13237500
b1000010010 #
1"
#13250000
0"
#13262500
b1000010011 #
1"
#13275000
0"
#13287500
b1000010100 #
1"
#13300000
0"
#13312500
b1000010101 #
1"
#13325000
0"
#13337500
b1000010110 #
1"
#13350000
0"
#13362500
b1000010111 #
1"
#13375000
0"
#13387500
b1000011000 #
1"
#13400000
0"
#13412500
b1000011001 #
1"
#13425000
0"
#13437500
b1000011010 #
1"
#13450000
0"
#13462500
b1000011011 #
1"
#13475000
0"
#13487500
b1000011100 #
1"
#13500000
0"
#13512500
b1000011101 #
1"
#13525000
0"
#13537500
b1000011110 #
1"
#13550000
0"
#13562500
b1000011111 #
1"
#13575000
0"
#13587500
b1000100000 #
1"
#13600000
0"
#13612500
b1000100001 #
1"
#13625000
0"
#13637500
b1000100010 #
1"
#13650000
0"
#13662500
b1000100011 #
1"
#13675000
0"
#13687500
b1000100100 #
1"
#13700000
0"
#13712500
b1000100101 #
1"
#13725000
0"
#13737500
b1000100110 #
1"
#13750000
0"
#13762500
b1000100111 #
1"
#13775000
0"
#13787500
b1000101000 #
1"
#13800000
0"
#13812500
b1000101001 #
1"
#13825000
0"
#13837500
b1000101010 #
1"
#13850000
0"
#13862500
b1000101011 #
1"
#13875000
0"
#13887500
b1000101100 #
1"
#13900000
0"
#13912500
b1000101101 #
1"
#13925000
0"
#13937500
b1000101110 #
1"
#13950000
0"
#13962500
b1000101111 #
1"
#13975000
0"
#13987500
b1000110000 #
1"
#14000000
0"
#14012500
b1000110001 #
1"
#14025000
0"
#14037500
b1000110010 #
1"
#14050000
0"
#14062500
b1000110011 #
1"
#14075000
0"
#14087500
b1000110100 #
1"
#14100000
0"
#14112500
b1000110101 #
1"
#14125000
0"
#14137500
b1000110110 #
1"
#14150000
0"
#14162500
b1000110111 #
1"
#14175000
0"
#14187500
b1000111000 #
1"
#14200000
0"
#14212500
b1000111001 #
1"
#14225000
0"
#14237500
b1000111010 #
1"
#14250000
0"
#14262500
b1000111011 #
1"
#14275000
0"
#14287500
b1000111100 #
1"
#14300000
0"
#14312500
b1000111101 #
1"
#14325000
0"
#14337500
b1000111110 #
1"
#14350000
0"
#14362500
b1000111111 #
1"
#14375000
0"
#14387500
b1001000000 #
1"
#14400000
0"
#14412500
b1001000001 #
1"
#14425000
0"
#14437500
b1001000010 #
1"
#14450000
0"
#14462500
b1001000011 #
1"
#14475000
0"
#14487500
b1001000100 #
1"
#14500000
0"
#14512500
b1001000101 #
1"
#14525000
0"
#14537500
b1001000110 #
1"
#14550000
0"
#14562500
b1001000111 #
1"
#14575000
0"
#14587500
b1001001000 #
1"
#14600000
0"
#14612500
b1001001001 #
1"
#14625000
0"
#14637500
b1001001010 #
1"
#14650000
0"
#14662500
b1001001011 #
1"
#14675000
0"
#14687500
b1001001100 #
1"
#14700000
0"
#14712500
b1001001101 #
1"
#14725000
0"
#14737500
b1001001110 #
1"
#14750000
0"
#14762500
b1001001111 #
1"
#14775000
0"
#14787500
b1001010000 #
1"
#14800000
0"
#14812500
b1001010001 #
1"
#14825000
0"
#14837500
b1001010010 #
1"
#14850000
0"
#14862500
b1001010011 #
1"
#14875000
0"
#14887500
b1001010100 #
1"
#14900000
0"
#14912500
b1001010101 #
1"
#14925000
0"
#14937500
b1001010110 #
1"
#14950000
0"
#14962500
b1001010111 #
1"
#14975000
0"
#14987500
b1001011000 #
1"
#15000000
0"
#15012500
b1001011001 #
1"
#15025000
0"
#15037500
b1001011010 #
1"
#15050000
0"
#15062500
b1001011011 #
1"
#15075000
0"
#15087500
b1001011100 #
1"
#15100000
0"
#15112500
b1001011101 #
1"
#15125000
0"
#15137500
b1001011110 #
1"
#15150000
0"
#15162500
b1001011111 #
1"
#15175000
0"
#15187500
b1001100000 #
1"
#15200000
0"
#15212500
b1001100001 #
1"
#15225000
0"
#15237500
b1001100010 #
1"
#15250000
0"
#15262500
b1001100011 #
1"
#15275000
0"
#15287500
b1001100100 #
1"
#15300000
0"
#15312500
b1001100101 #
1"
#15325000
0"
#15337500
b1001100110 #
1"
#15350000
0"
#15362500
b1001100111 #
1"
#15375000
0"
#15387500
b1001101000 #
1"
#15400000
0"
#15412500
b1001101001 #
1"
#15425000
0"
#15437500
b1001101010 #
1"
#15450000
0"
#15462500
b1001101011 #
1"
#15475000
0"
#15487500
b1001101100 #
1"
#15500000
0"
#15512500
b1001101101 #
1"
#15525000
0"
#15537500
b1001101110 #
1"
#15550000
0"
#15562500
b1001101111 #
1"
#15575000
0"
#15587500
b1001110000 #
1"
#15600000
0"
#15612500
b1001110001 #
1"
