rtl/modules/Debouncer.v
// Debouncer module that filters out noise from a noisy input signal by sampling
// it over multiple clock cycles. The output `stable_signal` becomes high when 
// the last N consecutive samples are all 1s, and low when they are all 0s. 
// It uses a shift register to store the past N samples, and a reset sets the 
// signal to a known state.

module Debouncer (
    input clk,
    input reset,
    input noisy_signal,
    output reg stable_signal
);
    parameter N = 8; // Number of samples in the shift register
    reg [N-1:0] shift_reg; // Shift register that holds the last n consecutive states  

    always @(posedge clk or posedge reset) 
    begin
        if (reset) begin
             shift_reg <= 0;
             stable_signal <= 0;
        end else begin
             shift_reg <= {shift_reg[N-2:0], noisy_signal};
             if (shift_reg == {N{1'b1}}) // Is it all consecutive 1s?
                  stable_signal <= 1;
             else if (shift_reg == {N{1'b0}}) // or is it 0s
                  stable_signal <= 0;
        end
    end
endmodule

testbench/Debouncer_tb.v
`timescale 1ns / 1ps

module Debouncer_tb;
    reg clk;
    reg reset;
    reg noisy_signal;
    wire stable_signal;

    Debouncer uut (
        .clk(clk),
        .reset(reset),
        .noisy_signal(noisy_signal),
        .stable_signal(stable_signal)
    );

    // Clock generation (40 MHz)
    always #12.5 clk = ~clk;  // 40 MHz clock -> 25 ns period -> 12.5 ns half period

    initial begin
        clk = 0;
        reset = 0;
        noisy_signal = 0;

        reset = 1;
        #50 reset = 0;

        #100 noisy_signal = 1;
        #100 noisy_signal = 0;
        #100 noisy_signal = 1;
        #200 noisy_signal = 0;
        #100 noisy_signal = 1;

        #1000;

        $finish;
    end

    // Monitor the signals during the simulation
    initial begin
        $monitor("Time = %0t | reset = %b | noisy_signal = %b | stable_signal = %b", 
                 $time, reset, noisy_signal, stable_signal);
        $dumpfile("build/debouncer.vcd");
        $dumpvars(0, Debouncer_tb);

    end
endmodule

build/debouncer.vcd
$date
	Mon Dec 09 17:52:34 2024
$end
$version
	Icarus Verilog
$end
$timescale
	1ps
$end
$scope module Debouncer_tb $end
$var wire 1 ! stable_signal $end
$var reg 1 " clk $end
$var reg 1 # noisy_signal $end
$var reg 1 $ reset $end
$scope module uut $end
$var wire 1 " clk $end
$var wire 1 # noisy_signal $end
$var wire 1 $ reset $end
$var reg 8 % shift_reg [7:0] $end
$var reg 1 ! stable_signal $end
$upscope $end
$upscope $end
$enddefinitions $end
#0
$dumpvars
b0 %
1$
0#
0"
0!
$end
#12500
1"
#25000
0"
#37500
1"
#50000
0"
0$
#62500
1"
#75000
0"
#87500
1"
#100000
0"
#112500
1"
#125000
0"
#137500
1"
#150000
0"
1#
#162500
b1 %
1"
#175000
0"
#187500
b11 %
1"
#200000
0"
#212500
b111 %
1"
#225000
0"
#237500
b1111 %
1"
#250000
0"
0#
#262500
b11110 %
1"
#275000
0"
#287500
b111100 %
1"
#300000
0"
#312500
b1111000 %
1"
#325000
0"
#337500
b11110000 %
1"
#350000
0"
1#
#362500
b11100001 %
1"
#375000
0"
#387500
b11000011 %
1"
#400000
0"
#412500
b10000111 %
1"
#425000
0"
#437500
b1111 %
1"
#450000
0"
#462500
b11111 %
1"
#475000
0"
#487500
b111111 %
1"
#500000
0"
#512500
b1111111 %
1"
#525000
0"
#537500
b11111111 %
1"
#550000
0"
0#
#562500
1!
b11111110 %
1"
#575000
0"
#587500
b11111100 %
1"
#600000
0"
#612500
b11111000 %
1"
#625000
0"
#637500
b11110000 %
1"
#650000
0"
1#
#662500
b11100001 %
1"
#675000
0"
#687500
b11000011 %
1"
#700000
0"
#712500
b10000111 %
1"
#725000
0"
#737500
b1111 %
1"
#750000
0"
#762500
b11111 %
1"
#775000
0"
#787500
b111111 %
1"
#800000
0"
#812500
b1111111 %
1"
#825000
0"
#837500
b11111111 %
1"
